Metadata-Version: 2.1
Name: hid_ups
Version: 0.7.0
Summary: A Python library for interacting with USB HID UPS devices.
Author-email: Desultory <dev@pyl.onl>
Project-URL: Homepage, https://github.com/desultory/hid_ups
Project-URL: Issues, https://github.com/desultory/pycpio/hid_ups
Classifier: Programming Language :: Python :: 3
Classifier: License :: OSI Approved :: GNU General Public License v2 (GPLv2)
Classifier: Operating System :: OS Independent
Requires-Python: >=3.11
License-File: LICENSE
Requires-Dist: zenlib>=1.7.1
